{
    "name": "Big Rich Media Content PDP",
    "description": "Big Rich Media Content Module which will used on pdp",
    "group": "assets",
    "attribute_definition_groups": [
        {
            "id": "data",
            "name": "General Info",
            "description": "please give the following data.",
            "attribute_definitions": [
                {
                    "id": "headline",
                    "name": "Headline",
                    "type": "string",
                    "required": true
                },
                {
                    "id": "contentCopy",
                    "name": "Content Copy",
                    "type" : "string",
                    "required": true
                },
                {
                    "id": "ImageOrVideoPosition",
                    "name": "Position of image of video",
                    "type": "enum",
                    "values": ["top", "middle", "bottom"],
                    "default_value": "top",
                    "required": false
                },
                {
                    "id": "headingPosition",
                    "name": "Heading Position",
                    "type": "enum",
                    "values": ["left", "right"],
                    "default_value": "left",
                    "required": false
                }
            ]
        },
        {
            "id": "videoDetails",
            "name": "Video Details",
            "description": "Please provide the following video data.",
            "attribute_definitions": [
                {
                    "id": "url",
                    "name": "Video URL",
                    "type": "string",
                    "required": false
                },
                {
                    "id": "width",
                    "name": "Video Width",
                    "type": "string",
                    "required": false
                },
                {
                    "id": "height",
                    "name": "Video Height",
                    "type": "string",
                    "required": false
                }
            ]
        },
        {
            "id": "image_data",
            "name": "Image focus points for desktop",
            "description": "please select image",
            "attribute_definitions": [
                {
                    "id": "image",
                    "name": "Image",
                    "type": "image",
                    "required": false
                }
            ]
        }
    ],
    "region_definitions": []
}